{
    "data": [
        {
            "name": "2023-09-30",
            "profit": 167162.36
        },
        {
            "name": "2023-10-01",
            "profit": 385918.72
        },
        {
            "name": "2023-10-02",
            "profit": 185487.12
        },
        {
            "name": "2023-10-03",
            "profit": 485126.33
        },
        {
            "name": "2023-10-04",
            "profit": 167162.36
        },
        {
            "name": "2023-10-05",
            "profit": 578812.05
        },
        {
            "name": "2023-10-06",
            "profit": 315899.11
        },
        {
            "name": "2023-10-07",
            "profit": 97142.75
        },
        {
            "name": "2023-10-08",
            "profit": 404243.48
        },
        {
            "name": "2023-10-09",
            "profit": 118791.98
        },
        {
            "name": "2023-10-10",
            "profit": 366334.35
        },
        {
            "name": "2023-10-11",
            "profit": 366334.35
        },
        {
            "name": "2023-10-12",
            "profit": 366334.35
        },
        {
            "name": "2023-10-13",
            "profit": 97142.75
        },
        {
            "name": "2023-10-14",
            "profit": 385918.72
        },
        {
            "name": "2023-10-15",
            "profit": 364269.49
        },
        {
            "name": "2023-10-16",
            "profit": 118791.98
        },
        {
            "name": "2023-10-17",
            "profit": 356139.54
        },
        {
            "name": "2023-10-18",
            "profit": 185487.12
        },
        {
            "name": "2023-10-19",
            "profit": 118791.98
        },
        {
            "name": "2023-10-20",
            "profit": 396113.53
        },
        {
            "name": "2023-10-21",
            "profit": 126921.93
        },
        {
            "name": "2023-10-22",
            "profit": 185487.12
        },
        {
            "name": "2023-10-23",
            "profit": 758318.16
        },
        {
            "name": "2023-10-24",
            "profit": 185487.12
        },
        {
            "name": "2023-10-25",
            "profit": 444483.91
        },
        {
            "name": "2023-10-26",
            "profit": 0.0
        },
        {
            "name": "2023-10-27",
            "profit": 0.0
        },
        {
            "name": "2023-10-28",
            "profit": 0.0
        },
        {
            "name": "2023-10-29",
            "profit": 0.0
        },
        {
            "name": "2023-10-30",
            "profit": 374464.3
        },
        {
            "name": "2023-10-31",
            "profit": 315899.11
        }
    ]
}